AUTHORS
CHANGES.rst
LICENSE
MANIFEST.in
README.rst
TODO.md
debian8-dist.sh
setup.py
docs/.gitignore
docs/Makefile
docs/conf.py
docs/developer.rst
docs/index.rst
docs/intro.rst
docs/make.bat
pydfm/__init__.py
pydfm/core.py
pydfm/database.py
pydfm/file_hash.py
pydfm.egg-info/PKG-INFO
pydfm.egg-info/SOURCES.txt
pydfm.egg-info/dependency_links.txt
pydfm.egg-info/top_level.txt
scripts/pydfm
scripts/pydfm-nox
tests/test_file_hash.py
tests/data/test_file.bin
tests/data/test_file.empty
tests/data/test_file.txt
tests/data/test1/1
tests/data/test1/3
tests/data/test1/5
tests/data/test1/a/1
tests/data/test1/a/3
tests/data/test1/a/e/1
tests/data/test1/a/e/f/2
tests/data/test1/a/e/f/4
tests/data/test1/a/e/i/6
tests/data/test1/c/1.1
tests/data/test1/c/1.2
tests/data/test1/c/e/1
tests/data/test1/c/e/f/2
tests/data/test1/c/e/f/4
tests/data/test1/c/e/i/6
tests/data/test1/d/1.1
tests/data/test1/d/1.2
tests/data/test1/d/h/3
tests/data/test1/f/2
tests/data/test1/f/4
tests/data/test2/a/1
tests/data/test2/a/2
tests/data/test2/a/3
tests/data/test2/a/4
tests/data/test2/a/5
tests/data/test2/b/1
tests/data/test2/b/2
tests/data/test2/b/3
tests/data/test2/c/1
tests/data/test2/c/2
tests/data/test2/c/3
tests/data/test2/c/4
tests/data/test2/d/6.1
tests/data/test2/d/6.2
tests/data/test2/e/7
tests/data/test2/f/7
tests/data/test3/a/1.1
tests/data/test3/a/1.2
tests/data/test3/b1/1.1
tests/data/test3/b1/1.2
tests/data/test3/b1/2
tests/data/test3/b2/1.1
tests/data/test3/b2/1.2
tests/data/test3/b2/2
tests/data/test4/1.1
tests/data/test4/1.2
tests/data/test5/a1/1
tests/data/test5/a2/1